{
	"parameters" :
	{
	},
	"panels" :
	{
		"main_panel" :
		{
		"url":"https://vmiis.github.io/modules/panels/main.html",
		"name":"Bank Management",
		"columns":
		[
			{
				"sections":
				[
					{
						"name":"Woolworths Credit Card",
						"tasks":
						[
							{
								"module_id":"transaction_import",
								"name":"Transaction Import",
								"table_id":"20010375",
								"url":"https://tomli113.github.io/modules/personal/woolworths_credit_card/transaction_import.html"
							},
							{
								"module_id":"transaction_bi",
								"name":"Transaction bi",
								"table_id":"20010376",
								"url":"https://tomli113.github.io/modules/personal/woolworths_credit_card/transaction_bi.html"
							},
							{
								"module_id":"credit_query",
								"name":"Credit Query",
								"table_id":"20010375",
								"url":"https://tomli113.github.io/modules/personal/woolworths_credit_card/query_credit.html"
							},
							{
								"module_id":"debit_query",
								"name":"Debit Query",
								"table_id":"20010375",
								"url":"https://tomli113.github.io/modules/personal/woolworths_credit_card/query_debit.html"
							},
							{
								"module_id":"credit_chart",
								"name":"Credit Chart",
								"table_id":"20010375",
								"url":"https://tomli113.github.io/modules/personal/woolworths_credit_card/chart_credit.html"
							},
							{
								"module_id":"debit_chart",
								"name":"Debit Chart",
								"table_id":"20010375",
								"url":"https://tomli113.github.io/modules/personal/woolworths_credit_card/chart_debit.html"
							}

						]
					}
				]
			}
		]
	}
	}
}
